diffcolor
