Metadata-Version: 2.1
Name: diffcolor
Version: 0.0.2
Summary: compare text and show the difference with color.
Home-page: https://github.com/sintrb/diffcolor/
Author: trb
Author-email: sintrb@gmail.com
License: UNKNOWN
Keywords: color,diff,comapre
Platform: UNKNOWN
